<?xml version="1.0" ?><summary fileFormatVersion="103"><hierarchy superClass="java.lang.Object"><interface name="android.os.Parcelable"></interface></hierarchy><methods><method id="android.graphics.Bitmap copy(android.graphics.Bitmap$Config,boolean)"><flows><flow isAlias="true"><from sourceSinkType="Parameter" ParameterIndex="0" BaseType="android.graphics.Bitmap$Config" AccessPath="[&lt;android.graphics.Bitmap$Config: int nativeInt&gt;]" AccessPathTypes="[int]"></from><to sourceSinkType="Return" BaseType="android.graphics.Bitmap" taintSubFields="true"></to></flow><flow isAlias="true"><from sourceSinkType="Parameter" ParameterIndex="1" BaseType="boolean"></from><to sourceSinkType="Return" BaseType="android.graphics.Bitmap" taintSubFields="true"></to></flow><flow isAlias="true"><from sourceSinkType="Field" BaseType="android.graphics.Bitmap" AccessPath="[&lt;android.graphics.Bitmap: long mNativePtr&gt;]" AccessPathTypes="[long]"></from><to sourceSinkType="Return" BaseType="android.graphics.Bitmap" taintSubFields="true"></to></flow><flow isAlias="false"><from sourceSinkType="Field" BaseType="android.graphics.Bitmap" AccessPath="[&lt;android.graphics.Bitmap: int mDensity&gt;]" AccessPathTypes="[int]"></from><to sourceSinkType="Return" BaseType="android.graphics.Bitmap" AccessPath="[&lt;android.graphics.Bitmap: int mDensity&gt;]" AccessPathTypes="[int]" taintSubFields="true"></to></flow><flow isAlias="false"><from sourceSinkType="Field" BaseType="android.graphics.Bitmap" AccessPath="[&lt;android.graphics.Bitmap: boolean mRequestPremultiplied&gt;]" AccessPathTypes="[boolean]"></from><to sourceSinkType="Return" BaseType="android.graphics.Bitmap" AccessPath="[&lt;java.lang.Object: boolean mPremultiplied&gt;]" AccessPathTypes="[boolean]" taintSubFields="true"></to></flow></flows></method><method id="void copyPixelsFromBuffer(java.nio.Buffer)"><flows><flow isAlias="true"><from sourceSinkType="Parameter" ParameterIndex="0" BaseType="java.nio.Buffer"></from><to sourceSinkType="GapBaseObject" BaseType="java.nio.Buffer" gap="10"></to></flow><flow isAlias="true"><from sourceSinkType="Field" BaseType="java.nio.Buffer" gap="10"></from><to sourceSinkType="GapBaseObject" BaseType="java.nio.Buffer" gap="11"></to></flow><flow isAlias="true"><from sourceSinkType="Field" BaseType="java.nio.Buffer" gap="12"></from><to sourceSinkType="Parameter" ParameterIndex="0" BaseType="java.nio.Buffer" taintSubFields="true"></to></flow><flow isAlias="true"><from sourceSinkType="Field" BaseType="java.nio.Buffer" gap="11"></from><to sourceSinkType="GapBaseObject" BaseType="java.nio.Buffer" gap="12"></to></flow><flow isAlias="false"><from sourceSinkType="Return" BaseType="int" gap="11"></from><to sourceSinkType="Parameter" ParameterIndex="0" BaseType="int" gap="12" taintSubFields="true"></to></flow></flows></method><method id="void copyPixelsToBuffer(java.nio.Buffer)"><flows><flow isAlias="true"><from sourceSinkType="Parameter" ParameterIndex="0" BaseType="java.nio.Buffer"></from><to sourceSinkType="GapBaseObject" BaseType="java.nio.Buffer" gap="13"></to></flow><flow isAlias="true"><from sourceSinkType="Field" BaseType="java.nio.Buffer" gap="14"></from><to sourceSinkType="GapBaseObject" BaseType="java.nio.Buffer" gap="15"></to></flow><flow isAlias="true"><from sourceSinkType="Field" BaseType="java.nio.Buffer" gap="15"></from><to sourceSinkType="Parameter" ParameterIndex="0" BaseType="java.nio.Buffer" taintSubFields="true"></to></flow><flow isAlias="false"><from sourceSinkType="Return" BaseType="int" gap="14"></from><to sourceSinkType="Parameter" ParameterIndex="0" BaseType="int" gap="15" taintSubFields="true"></to></flow><flow isAlias="true"><from sourceSinkType="Field" BaseType="java.nio.Buffer" gap="13"></from><to sourceSinkType="GapBaseObject" BaseType="java.nio.Buffer" gap="14"></to></flow></flows></method><method id="android.graphics.Bitmap createAshmemBitmap(android.graphics.Bitmap$Config)"><flows><flow isAlias="true"><from sourceSinkType="Parameter" ParameterIndex="0" BaseType="android.graphics.Bitmap$Config" AccessPath="[&lt;android.graphics.Bitmap$Config: int nativeInt&gt;]" AccessPathTypes="[int]"></from><to sourceSinkType="Return" BaseType="android.graphics.Bitmap" taintSubFields="true"></to></flow><flow isAlias="false"><from sourceSinkType="Field" BaseType="android.graphics.Bitmap" AccessPath="[&lt;android.graphics.Bitmap: boolean mRequestPremultiplied&gt;]" AccessPathTypes="[boolean]"></from><to sourceSinkType="Return" BaseType="android.graphics.Bitmap" AccessPath="[&lt;java.lang.Object: boolean mPremultiplied&gt;]" AccessPathTypes="[boolean]" taintSubFields="true"></to></flow><flow isAlias="true"><from sourceSinkType="Field" BaseType="android.graphics.Bitmap" AccessPath="[&lt;android.graphics.Bitmap: long mNativePtr&gt;]" AccessPathTypes="[long]"></from><to sourceSinkType="Return" BaseType="android.graphics.Bitmap" taintSubFields="true"></to></flow><flow isAlias="false"><from sourceSinkType="Field" BaseType="android.graphics.Bitmap" AccessPath="[&lt;android.graphics.Bitmap: int mDensity&gt;]" AccessPathTypes="[int]"></from><to sourceSinkType="Return" BaseType="android.graphics.Bitmap" AccessPath="[&lt;android.graphics.Bitmap: int mDensity&gt;]" AccessPathTypes="[int]" taintSubFields="true"></to></flow></flows></method><method id="android.graphics.Bitmap createAshmemBitmap()"><flows><flow isAlias="true"><from sourceSinkType="Field" BaseType="android.graphics.Bitmap" AccessPath="[&lt;android.graphics.Bitmap: long mNativePtr&gt;]" AccessPathTypes="[long]"></from><to sourceSinkType="Return" BaseType="android.graphics.Bitmap" taintSubFields="true"></to></flow><flow isAlias="false"><from sourceSinkType="Field" BaseType="android.graphics.Bitmap" AccessPath="[&lt;android.graphics.Bitmap: int mDensity&gt;]" AccessPathTypes="[int]"></from><to sourceSinkType="Return" BaseType="android.graphics.Bitmap" AccessPath="[&lt;android.graphics.Bitmap: int mDensity&gt;]" AccessPathTypes="[int]" taintSubFields="true"></to></flow><flow isAlias="false"><from sourceSinkType="Field" BaseType="android.graphics.Bitmap" AccessPath="[&lt;android.graphics.Bitmap: boolean mRequestPremultiplied&gt;]" AccessPathTypes="[boolean]"></from><to sourceSinkType="Return" BaseType="android.graphics.Bitmap" AccessPath="[&lt;java.lang.Object: boolean mPremultiplied&gt;]" AccessPathTypes="[boolean]" taintSubFields="true"></to></flow></flows></method><method id="android.graphics.Bitmap createBitmap(android.util.DisplayMetrics,int[],int,int,android.graphics.Bitmap$Config)"><flows><flow isAlias="false"><from sourceSinkType="Parameter" ParameterIndex="3" BaseType="int"></from><to sourceSinkType="Return" BaseType="android.graphics.Bitmap" AccessPath="[&lt;android.graphics.Bitmap: int mHeight&gt;]" AccessPathTypes="[int]" taintSubFields="true"></to></flow></flows></method><method id="android.graphics.Bitmap createBitmap(android.graphics.Picture)"><flows><flow isAlias="false"><from sourceSinkType="Parameter" ParameterIndex="0" BaseType="android.graphics.Picture" AccessPath="[&lt;android.graphics.Picture: long mNativePicture&gt;]" AccessPathTypes="[long]"></from><to sourceSinkType="Return" BaseType="android.graphics.Bitmap" AccessPath="[&lt;android.graphics.Bitmap: int mHeight&gt;]" AccessPathTypes="[int]" taintSubFields="true"></to></flow><flow isAlias="false"><from sourceSinkType="Parameter" ParameterIndex="0" BaseType="android.graphics.Picture" AccessPath="[&lt;android.graphics.Picture: long mNativePicture&gt;]" AccessPathTypes="[long]"></from><to sourceSinkType="Return" BaseType="android.graphics.Bitmap" AccessPath="[&lt;android.graphics.Bitmap: int mWidth&gt;]" AccessPathTypes="[int]" taintSubFields="true"></to></flow></flows></method><method id="android.graphics.Bitmap createBitmap(int[],int,int,int,int,android.graphics.Bitmap$Config)"><flows><flow isAlias="false"><from sourceSinkType="Parameter" ParameterIndex="3" BaseType="int"></from><to sourceSinkType="Return" BaseType="android.graphics.Bitmap" AccessPath="[&lt;android.graphics.Bitmap: int mWidth&gt;]" AccessPathTypes="[int]" taintSubFields="true"></to></flow><flow isAlias="false"><from sourceSinkType="Parameter" ParameterIndex="4" BaseType="int"></from><to sourceSinkType="Return" BaseType="android.graphics.Bitmap" AccessPath="[&lt;android.graphics.Bitmap: int mHeight&gt;]" AccessPathTypes="[int]" taintSubFields="true"></to></flow></flows></method><method id="android.graphics.Bitmap createBitmap(android.graphics.Picture,int,int,android.graphics.Bitmap$Config)"><flows><flow isAlias="false"><from sourceSinkType="Parameter" ParameterIndex="0" BaseType="android.graphics.Picture" AccessPath="[&lt;android.graphics.Picture: android.graphics.Picture$PictureCanvas mRecordingCanvas&gt;, &lt;android.graphics.Picture$PictureCanvas: boolean mHoldsHwBitmap&gt;]" AccessPathTypes="[android.graphics.Picture$PictureCanvas, boolean]"></from><to sourceSinkType="Parameter" ParameterIndex="0" BaseType="android.graphics.Picture" AccessPath="[&lt;android.graphics.Picture: boolean mRequiresHwAcceleration&gt;]" AccessPathTypes="[boolean]" taintSubFields="true"></to></flow><flow isAlias="false"><from sourceSinkType="Parameter" ParameterIndex="1" BaseType="int"></from><to sourceSinkType="Return" BaseType="android.graphics.Bitmap" taintSubFields="true"></to></flow><flow isAlias="false"><from sourceSinkType="Parameter" ParameterIndex="2" BaseType="int"></from><to sourceSinkType="Return" BaseType="android.graphics.Bitmap" taintSubFields="true"></to></flow></flows></method><method id="android.graphics.Bitmap createBitmap(android.util.DisplayMetrics,int[],int,int,int,int,android.graphics.Bitmap$Config)"><flows><flow isAlias="false"><from sourceSinkType="Parameter" ParameterIndex="0" BaseType="android.util.DisplayMetrics" AccessPath="[&lt;android.util.DisplayMetrics: int densityDpi&gt;]" AccessPathTypes="[int]"></from><to sourceSinkType="Return" BaseType="android.graphics.Bitmap" AccessPath="[&lt;android.graphics.Bitmap: int mDensity&gt;]" AccessPathTypes="[int]" taintSubFields="true"></to></flow><flow isAlias="true"><from sourceSinkType="Parameter" ParameterIndex="2" BaseType="int"></from><to sourceSinkType="Return" BaseType="android.graphics.Bitmap" taintSubFields="true"></to></flow><flow isAlias="true"><from sourceSinkType="Parameter" ParameterIndex="3" BaseType="int"></from><to sourceSinkType="Return" BaseType="android.graphics.Bitmap" taintSubFields="true"></to></flow><flow isAlias="true"><from sourceSinkType="Parameter" ParameterIndex="4" BaseType="int"></from><to sourceSinkType="Return" BaseType="android.graphics.Bitmap" taintSubFields="true"></to></flow><flow isAlias="true"><from sourceSinkType="Parameter" ParameterIndex="5" BaseType="int"></from><to sourceSinkType="Return" BaseType="android.graphics.Bitmap" taintSubFields="true"></to></flow><flow isAlias="true"><from sourceSinkType="Parameter" ParameterIndex="6" BaseType="android.graphics.Bitmap$Config" AccessPath="[&lt;android.graphics.Bitmap$Config: int nativeInt&gt;]" AccessPathTypes="[int]"></from><to sourceSinkType="Return" BaseType="android.graphics.Bitmap" taintSubFields="true"></to></flow></flows></method><method id="android.graphics.Bitmap createBitmap(int,int,android.graphics.Bitmap$Config,boolean)"><flows><flow isAlias="false"><from sourceSinkType="Parameter" ParameterIndex="0" BaseType="int"></from><to sourceSinkType="Return" BaseType="android.graphics.Bitmap" AccessPath="[&lt;android.graphics.Bitmap: int mWidth&gt;]" AccessPathTypes="[int]" taintSubFields="true"></to></flow><flow isAlias="false"><from sourceSinkType="Parameter" ParameterIndex="1" BaseType="int"></from><to sourceSinkType="Return" BaseType="android.graphics.Bitmap" AccessPath="[&lt;android.graphics.Bitmap: int mHeight&gt;]" AccessPathTypes="[int]" taintSubFields="true"></to></flow><flow isAlias="false"><from sourceSinkType="Parameter" ParameterIndex="3" BaseType="boolean"></from><to sourceSinkType="Return" BaseType="android.graphics.Bitmap" AccessPath="[&lt;java.lang.Object: boolean mHasAlpha&gt;]" AccessPathTypes="[boolean]" taintSubFields="true"></to></flow></flows></method><method id="android.graphics.Bitmap createBitmap(android.graphics.Bitmap,int,int,int,int)"><flows><flow isAlias="false"><from sourceSinkType="Parameter" ParameterIndex="3" BaseType="int"></from><to sourceSinkType="Return" BaseType="android.graphics.Bitmap" AccessPath="[&lt;android.graphics.Bitmap: int mWidth&gt;]" AccessPathTypes="[int]" taintSubFields="true"></to></flow><flow isAlias="false"><from sourceSinkType="Parameter" ParameterIndex="4" BaseType="int"></from><to sourceSinkType="Return" BaseType="android.graphics.Bitmap" AccessPath="[&lt;android.graphics.Bitmap: int mHeight&gt;]" AccessPathTypes="[int]" taintSubFields="true"></to></flow></flows></method><method id="android.graphics.Bitmap createBitmap(android.graphics.Bitmap,int,int,int,int,android.graphics.Matrix,boolean)"><flows><flow isAlias="false"><from sourceSinkType="Parameter" ParameterIndex="0" BaseType="android.graphics.Bitmap" AccessPath="[&lt;android.graphics.Bitmap: long mNativePtr&gt;]" AccessPathTypes="[long]"></from><to sourceSinkType="Return" BaseType="android.graphics.Bitmap" AccessPath="[&lt;android.graphics.Bitmap: int mDensity&gt;]" AccessPathTypes="[int]" taintSubFields="true"></to></flow><flow isAlias="true"><from sourceSinkType="Parameter" ParameterIndex="0" BaseType="android.graphics.Bitmap" AccessPath="[&lt;android.graphics.Bitmap: long mNativePtr&gt;]" AccessPathTypes="[long]"></from><to sourceSinkType="Return" BaseType="android.graphics.Bitmap" AccessPath="[&lt;android.graphics.Bitmap: android.graphics.ColorSpace mColorSpace&gt;]" AccessPathTypes="[android.graphics.ColorSpace]" taintSubFields="true"></to></flow><flow isAlias="false"><from sourceSinkType="Parameter" ParameterIndex="0" BaseType="android.graphics.Bitmap" AccessPath="[&lt;android.graphics.Bitmap: long mNativePtr&gt;]" AccessPathTypes="[long]"></from><to sourceSinkType="Return" BaseType="android.graphics.Bitmap" AccessPath="[&lt;java.lang.Object: boolean mPremultiplied&gt;]" AccessPathTypes="[boolean]" taintSubFields="true"></to></flow><flow isAlias="false"><from sourceSinkType="Parameter" ParameterIndex="0" BaseType="android.graphics.Bitmap" AccessPath="[&lt;android.graphics.Bitmap: int mDensity&gt;]" AccessPathTypes="[int]"></from><to sourceSinkType="Return" BaseType="android.graphics.Bitmap" AccessPath="[&lt;android.graphics.Bitmap: int mDensity&gt;]" AccessPathTypes="[int]" taintSubFields="true"></to></flow><flow isAlias="true"><from sourceSinkType="Parameter" ParameterIndex="0" BaseType="android.graphics.Bitmap" AccessPath="[&lt;android.graphics.Bitmap: android.graphics.ColorSpace mColorSpace&gt;]" AccessPathTypes="[android.graphics.ColorSpace]"></from><to sourceSinkType="Return" BaseType="android.graphics.Bitmap" AccessPath="[&lt;android.graphics.Bitmap: android.graphics.ColorSpace mColorSpace&gt;]" AccessPathTypes="[android.graphics.ColorSpace]" taintSubFields="true"></to></flow><flow isAlias="false"><from sourceSinkType="Parameter" ParameterIndex="0" BaseType="android.graphics.Bitmap" AccessPath="[&lt;android.graphics.Bitmap: boolean mRequestPremultiplied&gt;]" AccessPathTypes="[boolean]"></from><to sourceSinkType="Return" BaseType="android.graphics.Bitmap" AccessPath="[&lt;java.lang.Object: boolean mPremultiplied&gt;]" AccessPathTypes="[boolean]" taintSubFields="true"></to></flow><flow isAlias="false"><from sourceSinkType="Parameter" ParameterIndex="0" BaseType="android.graphics.Bitmap" AccessPath="[&lt;java.lang.Object: boolean mHasAlpha&gt;]" AccessPathTypes="[boolean]"></from><to sourceSinkType="Return" BaseType="android.graphics.Bitmap" AccessPath="[&lt;java.lang.Object: boolean mHasAlpha&gt;]" AccessPathTypes="[boolean]" taintSubFields="true"></to></flow><flow isAlias="false"><from sourceSinkType="Parameter" ParameterIndex="3" BaseType="int"></from><to sourceSinkType="Return" BaseType="android.graphics.Bitmap" AccessPath="[&lt;android.graphics.Bitmap: int mWidth&gt;]" AccessPathTypes="[int]" taintSubFields="true"></to></flow><flow isAlias="false"><from sourceSinkType="Parameter" ParameterIndex="4" BaseType="int"></from><to sourceSinkType="Return" BaseType="android.graphics.Bitmap" AccessPath="[&lt;android.graphics.Bitmap: int mHeight&gt;]" AccessPathTypes="[int]" taintSubFields="true"></to></flow></flows></method><method id="android.graphics.Bitmap createScaledBitmap(android.graphics.Bitmap,int,int,boolean)"><flows><flow isAlias="false"><from sourceSinkType="Parameter" ParameterIndex="0" BaseType="android.graphics.Bitmap" AccessPath="[&lt;android.graphics.Bitmap: int mHeight&gt;]" AccessPathTypes="[int]"></from><to sourceSinkType="Return" BaseType="android.graphics.Bitmap" AccessPath="[&lt;android.graphics.Bitmap: int mHeight&gt;]" AccessPathTypes="[int]" taintSubFields="true"></to></flow><flow isAlias="false"><from sourceSinkType="Parameter" ParameterIndex="0" BaseType="android.graphics.Bitmap" AccessPath="[&lt;android.graphics.Bitmap: int mWidth&gt;]" AccessPathTypes="[int]"></from><to sourceSinkType="Return" BaseType="android.graphics.Bitmap" AccessPath="[&lt;android.graphics.Bitmap: int mWidth&gt;]" AccessPathTypes="[int]" taintSubFields="true"></to></flow></flows></method><method id="android.graphics.Bitmap extractAlpha()"><flows><flow isAlias="true"><from sourceSinkType="Field" BaseType="android.graphics.Bitmap"></from><to sourceSinkType="Return" BaseType="android.graphics.Bitmap" taintSubFields="true"></to></flow></flows></method><method id="int getByteCount()"><flows><flow isAlias="false"><from sourceSinkType="Field" BaseType="android.graphics.Bitmap" AccessPath="[&lt;java.lang.Object: int mNativeBitmap&gt;]" AccessPathTypes="[int]"></from><to sourceSinkType="Return" BaseType="int" taintSubFields="true"></to></flow><flow isAlias="false"><from sourceSinkType="Field" BaseType="android.graphics.Bitmap" AccessPath="[&lt;android.graphics.Bitmap: int mHeight&gt;]" AccessPathTypes="[int]"></from><to sourceSinkType="Return" BaseType="int" taintSubFields="true"></to></flow></flows></method><method id="android.graphics.Color getColor(int,int)"><flows><flow isAlias="false"><from sourceSinkType="Parameter" ParameterIndex="0" BaseType="int"></from><to sourceSinkType="Return" BaseType="android.graphics.Color" AccessPath="[&lt;java.lang.Object: float a&gt;]" AccessPathTypes="[float]" taintSubFields="true"></to></flow><flow isAlias="false"><from sourceSinkType="Parameter" ParameterIndex="0" BaseType="int"></from><to sourceSinkType="Return" BaseType="android.graphics.Color" AccessPath="[&lt;java.lang.Object: float b&gt;]" AccessPathTypes="[int]" taintSubFields="true"></to></flow><flow isAlias="false"><from sourceSinkType="Parameter" ParameterIndex="0" BaseType="int"></from><to sourceSinkType="Return" BaseType="android.graphics.Color" AccessPath="[&lt;java.lang.Object: float g&gt;]" AccessPathTypes="[int]" taintSubFields="true"></to></flow><flow isAlias="false"><from sourceSinkType="Parameter" ParameterIndex="0" BaseType="int"></from><to sourceSinkType="Return" BaseType="android.graphics.Color" AccessPath="[&lt;java.lang.Object: float r&gt;]" AccessPathTypes="[int]" taintSubFields="true"></to></flow><flow isAlias="false"><from sourceSinkType="Parameter" ParameterIndex="1" BaseType="int"></from><to sourceSinkType="Return" BaseType="android.graphics.Color" AccessPath="[&lt;java.lang.Object: float r&gt;]" AccessPathTypes="[int]" taintSubFields="true"></to></flow><flow isAlias="false"><from sourceSinkType="Parameter" ParameterIndex="1" BaseType="int"></from><to sourceSinkType="Return" BaseType="android.graphics.Color" AccessPath="[&lt;java.lang.Object: float g&gt;]" AccessPathTypes="[int]" taintSubFields="true"></to></flow><flow isAlias="false"><from sourceSinkType="Parameter" ParameterIndex="1" BaseType="int"></from><to sourceSinkType="Return" BaseType="android.graphics.Color" AccessPath="[&lt;java.lang.Object: float a&gt;]" AccessPathTypes="[int]" taintSubFields="true"></to></flow><flow isAlias="false"><from sourceSinkType="Parameter" ParameterIndex="1" BaseType="int"></from><to sourceSinkType="Return" BaseType="android.graphics.Color" AccessPath="[&lt;java.lang.Object: float b&gt;]" AccessPathTypes="[int]" taintSubFields="true"></to></flow><flow isAlias="false"><from sourceSinkType="Field" BaseType="android.graphics.Bitmap" AccessPath="[&lt;android.graphics.Bitmap: long mNativePtr&gt;]" AccessPathTypes="[long]"></from><to sourceSinkType="Return" BaseType="android.graphics.Color" AccessPath="[&lt;java.lang.Object: float b&gt;]" AccessPathTypes="[int]" taintSubFields="true"></to></flow><flow isAlias="false"><from sourceSinkType="Field" BaseType="android.graphics.Bitmap" AccessPath="[&lt;android.graphics.Bitmap: long mNativePtr&gt;]" AccessPathTypes="[long]"></from><to sourceSinkType="Return" BaseType="android.graphics.Color" AccessPath="[&lt;java.lang.Object: float g&gt;]" AccessPathTypes="[int]" taintSubFields="true"></to></flow><flow isAlias="false"><from sourceSinkType="Field" BaseType="android.graphics.Bitmap" AccessPath="[&lt;android.graphics.Bitmap: long mNativePtr&gt;]" AccessPathTypes="[long]"></from><to sourceSinkType="Return" BaseType="android.graphics.Color" AccessPath="[&lt;java.lang.Object: float a&gt;]" AccessPathTypes="[float]" taintSubFields="true"></to></flow><flow isAlias="false"><from sourceSinkType="Field" BaseType="android.graphics.Bitmap" AccessPath="[&lt;android.graphics.Bitmap: long mNativePtr&gt;]" AccessPathTypes="[long]"></from><to sourceSinkType="Return" BaseType="android.graphics.Color" AccessPath="[&lt;java.lang.Object: float r&gt;]" AccessPathTypes="[int]" taintSubFields="true"></to></flow></flows></method><method id="byte[] getNinePatchChunk()"><flows><flow isAlias="false"><from sourceSinkType="Field" BaseType="android.graphics.Bitmap" AccessPath="[&lt;android.graphics.Bitmap: byte[] mNinePatchChunk&gt;]" AccessPathTypes="[byte[]]"></from><to sourceSinkType="Return" BaseType="byte[]" taintSubFields="true"></to></flow></flows></method><method id="android.graphics.NinePatch$InsetStruct getNinePatchInsets()"><flows><flow isAlias="true"><from sourceSinkType="Field" BaseType="android.graphics.Bitmap" AccessPath="[&lt;android.graphics.Bitmap: android.graphics.NinePatch$InsetStruct mNinePatchInsets&gt;]" AccessPathTypes="[android.graphics.NinePatch$InsetStruct]"></from><to sourceSinkType="Return" BaseType="android.graphics.NinePatch$InsetStruct" taintSubFields="true"></to></flow></flows></method><method id="void getOpticalInsets(android.graphics.Rect)"><flows><flow isAlias="true"><from sourceSinkType="Field" BaseType="android.graphics.Bitmap" AccessPath="[&lt;android.graphics.Bitmap: android.graphics.NinePatch$InsetStruct mNinePatchInsets&gt;, &lt;android.graphics.NinePatch$InsetStruct: android.graphics.Rect opticalRect&gt;]" AccessPathTypes="[android.graphics.NinePatch$InsetStruct, android.graphics.Rect]"></from><to sourceSinkType="Parameter" ParameterIndex="0" BaseType="android.graphics.Rect" taintSubFields="true"></to></flow></flows></method><method id="int getPixel(int,int)"><flows><flow isAlias="false"><from sourceSinkType="Parameter" ParameterIndex="0" BaseType="int"></from><to sourceSinkType="Return" BaseType="int" taintSubFields="true"></to></flow><flow isAlias="false"><from sourceSinkType="Parameter" ParameterIndex="1" BaseType="int"></from><to sourceSinkType="Return" BaseType="int" taintSubFields="true"></to></flow><flow isAlias="false"><from sourceSinkType="Field" BaseType="android.graphics.Bitmap" AccessPath="[&lt;android.graphics.Bitmap: long mNativePtr&gt;]" AccessPathTypes="[long]"></from><to sourceSinkType="Return" BaseType="int" taintSubFields="true"></to></flow></flows></method><method id="boolean hasAlpha()"><flows><flow isAlias="false"><from sourceSinkType="Field" BaseType="android.graphics.Bitmap" AccessPath="[&lt;android.graphics.Bitmap: long mNativePtr&gt;]" AccessPathTypes="[long]"></from><to sourceSinkType="Return" BaseType="boolean" taintSubFields="true"></to></flow></flows></method><method id="boolean hasMipMap()"><flows><flow isAlias="false"><from sourceSinkType="Field" BaseType="android.graphics.Bitmap" AccessPath="[&lt;android.graphics.Bitmap: long mNativePtr&gt;]" AccessPathTypes="[long]"></from><to sourceSinkType="Return" BaseType="boolean" taintSubFields="true"></to></flow></flows></method><method id="boolean isMutable()"><flows><flow isAlias="false"><from sourceSinkType="Field" BaseType="android.graphics.Bitmap" AccessPath="[&lt;android.graphics.Bitmap: long mNativePtr&gt;]" AccessPathTypes="[long]"></from><to sourceSinkType="Return" BaseType="boolean" taintSubFields="true"></to></flow></flows></method><method id="boolean isPremultiplied()"><flows><flow isAlias="false"><from sourceSinkType="Field" BaseType="android.graphics.Bitmap" AccessPath="[&lt;android.graphics.Bitmap: long mNativePtr&gt;]" AccessPathTypes="[long]"></from><to sourceSinkType="Return" BaseType="boolean" taintSubFields="true"></to></flow></flows></method><method id="int scaleFromDensity(int,int,int)"><flows><flow isAlias="false"><from sourceSinkType="Parameter" ParameterIndex="0" BaseType="int"></from><to sourceSinkType="Return" BaseType="int" taintSubFields="true"></to></flow><flow isAlias="false"><from sourceSinkType="Parameter" ParameterIndex="1" BaseType="int"></from><to sourceSinkType="Return" BaseType="int" taintSubFields="true"></to></flow><flow isAlias="false"><from sourceSinkType="Parameter" ParameterIndex="2" BaseType="int"></from><to sourceSinkType="Return" BaseType="int" taintSubFields="true"></to></flow></flows></method><method id="void setColorSpace(android.graphics.ColorSpace)"><flows><flow isAlias="true"><from sourceSinkType="Parameter" ParameterIndex="0" BaseType="android.graphics.ColorSpace"></from><to sourceSinkType="GapBaseObject" BaseType="android.graphics.ColorSpace" gap="1"></to></flow><flow isAlias="true"><from sourceSinkType="Field" BaseType="android.graphics.ColorSpace" gap="5"></from><to sourceSinkType="Field" BaseType="android.graphics.Bitmap" AccessPath="[&lt;android.graphics.Bitmap: android.graphics.ColorSpace mColorSpace&gt;]" AccessPathTypes="[android.graphics.ColorSpace]" taintSubFields="true"></to></flow><flow isAlias="true"><from sourceSinkType="Field" BaseType="android.graphics.Bitmap" AccessPath="[&lt;android.graphics.Bitmap: android.graphics.ColorSpace mColorSpace&gt;]" AccessPathTypes="[android.graphics.ColorSpace]"></from><to sourceSinkType="GapBaseObject" BaseType="android.graphics.ColorSpace" gap="2"></to></flow><flow isAlias="true"><from sourceSinkType="Field" BaseType="android.graphics.ColorSpace" gap="5"></from><to sourceSinkType="GapBaseObject" BaseType="android.graphics.ColorSpace" gap="7"></to></flow><flow isAlias="true"><from sourceSinkType="Field" BaseType="android.graphics.ColorSpace" gap="6"></from><to sourceSinkType="GapBaseObject" BaseType="android.graphics.ColorSpace" gap="4"></to></flow><flow isAlias="true"><from sourceSinkType="Field" BaseType="android.graphics.Bitmap" AccessPath="[&lt;android.graphics.Bitmap: android.graphics.ColorSpace mColorSpace&gt;]" AccessPathTypes="[android.graphics.ColorSpace]"></from><to sourceSinkType="GapBaseObject" BaseType="android.graphics.ColorSpace" gap="3"></to></flow><flow isAlias="true"><from sourceSinkType="Field" BaseType="android.graphics.ColorSpace" gap="4"></from><to sourceSinkType="GapBaseObject" BaseType="android.graphics.ColorSpace" gap="3"></to></flow><flow isAlias="true"><from sourceSinkType="Field" BaseType="android.graphics.ColorSpace" gap="2"></from><to sourceSinkType="GapBaseObject" BaseType="android.graphics.ColorSpace" gap="4"></to></flow><flow isAlias="true"><from sourceSinkType="Field" BaseType="android.graphics.ColorSpace" gap="6"></from><to sourceSinkType="GapBaseObject" BaseType="android.graphics.ColorSpace" gap="7"></to></flow><flow isAlias="true"><from sourceSinkType="Field" BaseType="android.graphics.ColorSpace" gap="5"></from><to sourceSinkType="GapBaseObject" BaseType="android.graphics.ColorSpace" gap="3"></to></flow><flow isAlias="true"><from sourceSinkType="Field" BaseType="android.graphics.ColorSpace" gap="4"></from><to sourceSinkType="Field" BaseType="android.graphics.Bitmap" AccessPath="[&lt;android.graphics.Bitmap: android.graphics.ColorSpace mColorSpace&gt;]" AccessPathTypes="[android.graphics.ColorSpace]" taintSubFields="true"></to></flow><flow isAlias="true"><from sourceSinkType="Field" BaseType="android.graphics.ColorSpace" gap="7"></from><to sourceSinkType="GapBaseObject" BaseType="android.graphics.ColorSpace" gap="8"></to></flow><flow isAlias="true"><from sourceSinkType="Field" BaseType="android.graphics.ColorSpace" gap="4"></from><to sourceSinkType="GapBaseObject" BaseType="android.graphics.ColorSpace" gap="7"></to></flow><flow isAlias="true"><from sourceSinkType="Field" BaseType="android.graphics.ColorSpace" gap="2"></from><to sourceSinkType="GapBaseObject" BaseType="android.graphics.ColorSpace" gap="3"></to></flow><flow isAlias="true"><from sourceSinkType="Field" BaseType="android.graphics.ColorSpace" gap="4"></from><to sourceSinkType="GapBaseObject" BaseType="android.graphics.ColorSpace" gap="5"></to></flow><flow isAlias="true"><from sourceSinkType="Field" BaseType="android.graphics.ColorSpace" gap="6"></from><to sourceSinkType="Field" BaseType="android.graphics.Bitmap" AccessPath="[&lt;android.graphics.Bitmap: android.graphics.ColorSpace mColorSpace&gt;]" AccessPathTypes="[android.graphics.ColorSpace]" taintSubFields="true"></to></flow><flow isAlias="true"><from sourceSinkType="Field" BaseType="android.graphics.ColorSpace" gap="9"></from><to sourceSinkType="GapBaseObject" BaseType="android.graphics.ColorSpace" gap="8"></to></flow><flow isAlias="true"><from sourceSinkType="Field" BaseType="android.graphics.ColorSpace" gap="6"></from><to sourceSinkType="GapBaseObject" BaseType="android.graphics.ColorSpace" gap="3"></to></flow><flow isAlias="true"><from sourceSinkType="Field" BaseType="android.graphics.ColorSpace" gap="2"></from><to sourceSinkType="GapBaseObject" BaseType="android.graphics.ColorSpace" gap="7"></to></flow><flow isAlias="true"><from sourceSinkType="Field" BaseType="android.graphics.ColorSpace" gap="5"></from><to sourceSinkType="GapBaseObject" BaseType="android.graphics.ColorSpace" gap="6"></to></flow><flow isAlias="true"><from sourceSinkType="Field" BaseType="android.graphics.Bitmap" AccessPath="[&lt;android.graphics.Bitmap: android.graphics.ColorSpace mColorSpace&gt;]" AccessPathTypes="[android.graphics.ColorSpace]"></from><to sourceSinkType="GapBaseObject" BaseType="android.graphics.ColorSpace" gap="7"></to></flow></flows></method><method id="android.graphics.Bitmap wrapHardwareBuffer(android.hardware.HardwareBuffer,android.graphics.ColorSpace)"><flows><flow isAlias="false"><from sourceSinkType="Parameter" ParameterIndex="1" BaseType="android.graphics.ColorSpace" AccessPath="[&lt;android.graphics.ColorSpace$Rgb: long mNativePtr&gt;]" AccessPathTypes="[long]"></from><to sourceSinkType="Return" BaseType="android.graphics.Bitmap" taintSubFields="true"></to></flow></flows></method></methods><gaps><gap num="1" id="&lt;android.graphics.ColorSpace: long getNativeInstance()&gt;"></gap><gap num="2" id="&lt;android.graphics.ColorSpace: int getComponentCount()&gt;"></gap><gap num="3" id="&lt;android.graphics.ColorSpace: long getNativeInstance()&gt;"></gap><gap num="4" id="&lt;android.graphics.ColorSpace: int getComponentCount()&gt;"></gap><gap num="5" id="&lt;android.graphics.ColorSpace: float getMinValue(int)&gt;"></gap><gap num="6" id="&lt;android.graphics.ColorSpace: float getMaxValue(int)&gt;"></gap><gap num="7" id="&lt;android.graphics.ColorSpace: int getComponentCount()&gt;"></gap><gap num="8" id="&lt;android.graphics.ColorSpace: float getMinValue(int)&gt;"></gap><gap num="9" id="&lt;android.graphics.ColorSpace: float getMaxValue(int)&gt;"></gap><gap num="10" id="&lt;java.nio.Buffer: int remaining()&gt;"></gap><gap num="11" id="&lt;java.nio.Buffer: int position()&gt;"></gap><gap num="12" id="&lt;java.nio.Buffer: java.nio.Buffer position(int)&gt;"></gap><gap num="13" id="&lt;java.nio.Buffer: int remaining()&gt;"></gap><gap num="14" id="&lt;java.nio.Buffer: int position()&gt;"></gap><gap num="15" id="&lt;java.nio.Buffer: java.nio.Buffer position(int)&gt;"></gap></gaps></summary>